stix2generator/__init__.py
stix2generator/exceptions.py
stix2generator/logging.py
stix2generator/stix21_registry.json
stix2generator/stixcustom.py
stix2generator/utils.py
stix2generator/generation/__init__.py
stix2generator/generation/constraints.py
stix2generator/generation/generate_stix.py
stix2generator/generation/object_generator.py
stix2generator/generation/pattern_generator.py
stix2generator/generation/reference_graph_generator.py
stix2generator/generation/relationships.py
stix2generator/generation/semantics.py
stix2generator/generation/stix_generator.py
stix2generator/language/__init__.py
stix2generator/language/build_stix.py
stix2generator/language/builder.py
stix2_generator-0.2.0.dist-info/LICENSE.md
stix2_generator-0.2.0.dist-info/METADATA
stix2_generator-0.2.0.dist-info/WHEEL
stix2_generator-0.2.0.dist-info/entry_points.txt
stix2_generator-0.2.0.dist-info/top_level.txt
stix2_generator-0.2.0.dist-info/RECORD
