Metadata-Version: 2.1
Name: stix2-generator
Version: 0.2.0
Summary: Generate random STIX 2 content.
Home-page: https://github.com/oasis-open/cti-stix-generator
Author: OASIS Cyber Threat Intelligence Technical Committee
Author-email: cti-users@lists.oasis-open.org
Maintainer: Chris Lenk, Andy Chisholm
Maintainer-email: clenk@mitre.org, chisholm@mitre.org
License: BSD
Keywords: stix stix2 json generator generation stix2-generator
Platform: UNKNOWN
Classifier: Development Status :: 4 - Beta
Classifier: Intended Audience :: Developers
Classifier: License :: OSI Approved :: BSD License
Classifier: Programming Language :: Python :: 3
Classifier: Programming Language :: Python :: 3.6
Classifier: Programming Language :: Python :: 3.7
Classifier: Programming Language :: Python :: 3.8
Classifier: Programming Language :: Python :: 3.9
Requires-Python: >= 3.6
Requires-Dist: Faker
Requires-Dist: lark-parser
Requires-Dist: pytz
Requires-Dist: stix2 (>=3.0.0)
Provides-Extra: jupyter
Requires-Dist: jupyter ; extra == 'jupyter'
Requires-Dist: stix2-viz ; extra == 'jupyter'
Provides-Extra: tests
Requires-Dist: pytest ; extra == 'tests'
Requires-Dist: rdflib ; extra == 'tests'
